ab/__init__.py
ab/gpt/NNAlterCaption_8B.py
ab/gpt/NNAlterLayer.py
ab/gpt/NNAlter_30B_code_qw.py
ab/gpt/NNAlter_7B.py
ab/gpt/NNAlter_7B_code.py
ab/gpt/NNAlter_7B_code_olymp.py
ab/gpt/NNAlter_8B.py
ab/gpt/NNEval.py
ab/gpt/RAG_NNAlter_7b.py
ab/gpt/TuneAccPrediction.py
ab/gpt/TuneHyperparameters.py
ab/gpt/TuneNNGen.py
ab/gpt/TuneNNGen_1_3B_code.py
ab/gpt/TuneNNGen_1_3B_code_nngpt.py
ab/gpt/TuneNNGen_7B.py
ab/gpt/TuneNNGen_7B_code.py
ab/gpt/TuneNNGen_7B_code_olympic.py
ab/gpt/TuneNNGen_8B.py
ab/gpt/TuneRL.py
ab/gpt/__init__.py
ab/gpt/brute/README.md
ab/gpt/brute/__init__.py
ab/gpt/brute/ast/README.md
ab/gpt/brute/ast/__init__.py
ab/gpt/brute/ast/mutator/__init__.py
ab/gpt/brute/ast/mutator/config.py
ab/gpt/brute/ast/mutator/lemur_io.py
ab/gpt/brute/ast/mutator/orchestrator.py
ab/gpt/brute/ast/mutator/run_mutation.py
ab/gpt/brute/ast/mutator/core/__init__.py
ab/gpt/brute/ast/mutator/execution/__init__.py
ab/gpt/brute/ast/mutator/execution/apply_activation.py
ab/gpt/brute/ast/mutator/execution/apply_architectural.py
ab/gpt/brute/ast/mutator/execution/apply_dimension.py
ab/gpt/brute/ast/mutator/execution/apply_factory_mutations.py
ab/gpt/brute/ast/mutator/execution/apply_layer_type.py
ab/gpt/brute/ast/mutator/execution/apply_spatial.py
ab/gpt/brute/ast/mutator/execution/apply_symbolic.py
ab/gpt/brute/ast/mutator/execution/code_mutator.py
ab/gpt/brute/ast/mutator/execution/constants.py
ab/gpt/brute/ast/mutator/execution/validators.py
ab/gpt/brute/ast/mutator/planning/__init__.py
ab/gpt/brute/ast/mutator/planning/activation_planner.py
ab/gpt/brute/ast/mutator/planning/architectural_planner.py
ab/gpt/brute/ast/mutator/planning/architecture_patterns.py
ab/gpt/brute/ast/mutator/planning/base_planner.py
ab/gpt/brute/ast/mutator/planning/dimension_planner.py
ab/gpt/brute/ast/mutator/planning/fallback_planner.py
ab/gpt/brute/ast/mutator/planning/layer_planner.py
ab/gpt/brute/ast/mutator/planning/spatial_planner.py
ab/gpt/brute/ast/mutator/tracking/__init__.py
nn_gpt-1.0.3.dist-info/licenses/LICENSE
nn_gpt-1.0.3.dist-info/METADATA
nn_gpt-1.0.3.dist-info/WHEEL
nn_gpt-1.0.3.dist-info/top_level.txt
nn_gpt-1.0.3.dist-info/RECORD
