Metadata-Version: 2.4
Name: nn-gpt
Version: 1.0.3
Summary: LLM-Based Neural Network Generator
Author-email: ABrain One and contributors <AI@ABrain.one>
License: MIT License
Project-URL: Homepage, https://ABrain.one
Project-URL: Repository, https://github.com/ABrain-One/nn-gpt
Classifier: Programming Language :: Python :: 3
Classifier: License :: OSI Approved :: MIT License
Classifier: Operating System :: OS Independent
Requires-Python: >=3.10
License-File: LICENSE
Requires-Dist: wheel
Requires-Dist: torch==2.7.1
Requires-Dist: nn-dataset>=2.0.6
Requires-Dist: bitsandbytes>=0.45.0
Requires-Dist: peft>=0.14.0
Requires-Dist: gguf>=0.10.0
Requires-Dist: trl
Requires-Dist: sentence-transformers>=3.3.1
Requires-Dist: deepspeed>=0.16.3
Requires-Dist: faiss-cpu
Requires-Dist: overrides>=7.7.0
Provides-Extra: flash
Requires-Dist: flash_attn; extra == "flash"
Provides-Extra: stat
Requires-Dist: nn-stat; extra == "stat"
Provides-Extra: rag
Requires-Dist: nn-rag>=2.0.0; extra == "rag"
Dynamic: license-file
